symmatrix/__init__.py
symmatrix/version.py
symmatrix-0.1.0.dist-info/METADATA
symmatrix-0.1.0.dist-info/WHEEL
symmatrix-0.1.0.dist-info/top_level.txt
symmatrix-0.1.0.dist-info/RECORD
